{
  "version": "1.2",
  "manufacturer": "Cameo",
  "model": "CLM PAR COB 1",
  "type": "Par",
  "image": "",
  "productPage": "",
  "manual": "",
  "author": "Freasy",
  "channels": [
    {
      "name": "Red",
      "type": "Red"
    },
    {
      "name": "Green",
      "type": "Green"
    },
    {
      "name": "Blue",
      "type": "Blue"
    },
    {
      "name": "Colour Macro 1",
      "type": "Color",
      "capabilities": [
        {
          "min": "0",
          "max": "4",
          "name": "Blackout"
        },
        {
          "min": "5",
          "max": "36",
          "name": "Red"
        },
        {
          "min": "37",
          "max": "73",
          "name": "Green"
        },
        {
          "min": "74",
          "max": "110",
          "name": "Blue"
        },
        {
          "min": "111",
          "max": "147",
          "name": "Yellow"
        },
        {
          "min": "148",
          "max": "184",
          "name": "Magenta"
        },
        {
          "min": "185",
          "max": "221",
          "name": "Cyan"
        },
        {
          "min": "222",
          "max": "255",
          "name": "White"
        }
      ]
    },
    {
      "name": "Colour Macro 2",
      "type": "Color",
      "capabilities": [
        {
          "min": "0",
          "max": "4",
          "name": "Blackout"
        },
        {
          "min": "5",
          "max": "36",
          "name": "Red"
        },
        {
          "min": "37",
          "max": "73",
          "name": "Green"
        },
        {
          "min": "74",
          "max": "110",
          "name": "Blue"
        },
        {
          "min": "111",
          "max": "147",
          "name": "Yellow"
        },
        {
          "min": "148",
          "max": "184",
          "name": "Magenta"
        },
        {
          "min": "185",
          "max": "221",
          "name": "Cyan"
        },
        {
          "min": "222",
          "max": "255",
          "name": "White"
        }
      ]
    },
    {
      "name": "Colour Macro 3",
      "type": "Color",
      "capabilities": [
        {
          "min": "0",
          "max": "4",
          "name": "Blackout"
        },
        {
          "min": "5",
          "max": "36",
          "name": "Red"
        },
        {
          "min": "37",
          "max": "73",
          "name": "Green"
        },
        {
          "min": "74",
          "max": "110",
          "name": "Blue"
        },
        {
          "min": "111",
          "max": "147",
          "name": "Yellow"
        },
        {
          "min": "148",
          "max": "184",
          "name": "Magenta"
        },
        {
          "min": "185",
          "max": "221",
          "name": "Cyan"
        },
        {
          "min": "222",
          "max": "255",
          "name": "White"
        }
      ]
    },
    {
      "name": "Colour Macro 4",
      "type": "Color",
      "capabilities": [
        {
          "min": "0",
          "max": "4",
          "name": "Blackout"
        },
        {
          "min": "5",
          "max": "36",
          "name": "Red"
        },
        {
          "min": "37",
          "max": "73",
          "name": "Green"
        },
        {
          "min": "74",
          "max": "110",
          "name": "Blue"
        },
        {
          "min": "111",
          "max": "147",
          "name": "Yellow"
        },
        {
          "min": "148",
          "max": "184",
          "name": "Magenta"
        },
        {
          "min": "185",
          "max": "221",
          "name": "Cyan"
        },
        {
          "min": "222",
          "max": "255",
          "name": "White"
        }
      ]
    },
    {
      "name": "Power Out 1",
      "type": "Maintenance",
      "capabilities": [
        {
          "min": "0",
          "max": "127",
          "name": "Power out 1 OFF"
        },
        {
          "min": "128",
          "max": "255",
          "name": "Power out 1 ON"
        }
      ]
    },
    {
      "name": "Power Out 2",
      "type": "Maintenance",
      "capabilities": [
        {
          "min": "0",
          "max": "127",
          "name": "Power out 2 OFF"
        },
        {
          "min": "128",
          "max": "255",
          "name": "Power out 2 ON"
        }
      ]
    },
    {
      "name": "Red 1 + 2",
      "type": "Red"
    },
    {
      "name": "Green 1 + 2",
      "type": "Green"
    },
    {
      "name": "Blue 1 + 2",
      "type": "Blue"
    },
    {
      "name": "Red 3 + 4",
      "type": "Red"
    },
    {
      "name": "Green 3 + 4",
      "type": "Green"
    },
    {
      "name": "Blue 3 + 4",
      "type": "Blue"
    },
    {
      "name": "Master Dimmer",
      "type": "Intensity"
    },
    {
      "name": "Music Control / Strobe",
      "type": "Speed",
      "capabilities": [
        {
          "min": "0",
          "max": "0",
          "name": "Colour setting channel 1 - 3"
        },
        {
          "min": "1",
          "max": "128",
          "name": "Music control (sensitivity weak - strong)"
        },
        {
          "min": "129",
          "max": "255",
          "name": "Strobe (slow - fast)"
        }
      ]
    },
    {
      "name": "Programs",
      "type": "Color",
      "capabilities": [
        {
          "min": "0",
          "max": "15",
          "name": "CH4 - CH6 RGB"
        },
        {
          "min": "16",
          "max": "23",
          "name": "Red"
        },
        {
          "min": "24",
          "max": "31",
          "name": "Green"
        },
        {
          "min": "32",
          "max": "39",
          "name": "Blue"
        },
        {
          "min": "40",
          "max": "47",
          "name": "Yellow"
        },
        {
          "min": "48",
          "max": "55",
          "name": "Cyan"
        },
        {
          "min": "56",
          "max": "63",
          "name": "Magenta"
        },
        {
          "min": "64",
          "max": "71",
          "name": "White"
        },
        {
          "min": "72",
          "max": "79",
          "name": "Colour 1"
        },
        {
          "min": "80",
          "max": "87",
          "name": "Colour 2"
        },
        {
          "min": "88",
          "max": "95",
          "name": "Colour 3"
        },
        {
          "min": "96",
          "max": "103",
          "name": "Colour 4"
        },
        {
          "min": "104",
          "max": "111",
          "name": "Colour 5"
        },
        {
          "min": "112",
          "max": "119",
          "name": "Colour 6"
        },
        {
          "min": "120",
          "max": "127",
          "name": "Colour 7"
        },
        {
          "min": "128",
          "max": "135",
          "name": "Colour 8"
        },
        {
          "min": "136",
          "max": "143",
          "name": "Dream\n   \n   \n  "
        },
        {
          "min": "144",
          "max": "151",
          "name": "Meteor\n   \n   \n  "
        },
        {
          "min": "152",
          "max": "159",
          "name": "Fade\n   \n   \n  "
        },
        {
          "min": "160",
          "max": "167",
          "name": "Change\n   \n   \n  "
        },
        {
          "min": "168",
          "max": "175",
          "name": "Flow1\n   \n   \n  "
        },
        {
          "min": "176",
          "max": "183",
          "name": "Flow2\n   \n   \n  "
        },
        {
          "min": "184",
          "max": "191",
          "name": "Flow3\n   \n   \n  "
        },
        {
          "min": "192",
          "max": "199",
          "name": "Flow4\n   \n   \n  "
        },
        {
          "min": "200",
          "max": "207",
          "name": "Flow5\n   \n   \n  "
        },
        {
          "min": "208",
          "max": "215",
          "name": "Flow6\n   \n   \n  "
        },
        {
          "min": "216",
          "max": "223",
          "name": "Flow7\n   \n   \n  "
        },
        {
          "min": "224",
          "max": "231",
          "name": "Flow8\n   \n   \n   \n   \n   \n   \n  "
        },
        {
          "min": "232",
          "max": "239",
          "name": "Flow9\n   \n   \n   \n   \n   \n   \n  "
        },
        {
          "min": "240",
          "max": "255",
          "name": "Music Control\n   \n   \n   \n   \n   \n   \n   \n   \n  "
        }
      ]
    },
    {
      "name": "Strobe",
      "type": "Shutter",
      "capabilities": [
        {
          "min": "0",
          "max": "0",
          "name": "No function"
        },
        {
          "min": "1",
          "max": "255",
          "name": "Strobe (slow - fast)"
        }
      ]
    },
    {
      "name": "Red 1",
      "type": "Red"
    },
    {
      "name": "Green 1",
      "type": "Green"
    },
    {
      "name": "Blue 1",
      "type": "Blue"
    },
    {
      "name": "Red 2",
      "type": "Red"
    },
    {
      "name": "Green 2",
      "type": "Green"
    },
    {
      "name": "Blue 2",
      "type": "Blue"
    },
    {
      "name": "Red 3",
      "type": "Red"
    },
    {
      "name": "Green 3",
      "type": "Green"
    },
    {
      "name": "Blue 3",
      "type": "Blue"
    },
    {
      "name": "Red 4",
      "type": "Red"
    },
    {
      "name": "Green 4",
      "type": "Green"
    },
    {
      "name": "Blue 4",
      "type": "Blue"
    },
    {
      "name": "Sound Sensitivity",
      "type": "Effect",
      "capabilities": [
        {
          "min": "0",
          "max": "255",
          "name": "Sound sensitivity"
        }
      ]
    },
    {
      "name": "Speed",
      "type": "Speed",
      "capabilities": [
        {
          "min": "0",
          "max": "255",
          "name": "Speed (slow to fast)"
        }
      ]
    },
    {
      "name": "No function 1",
      "type": "Unknown"
    },
    {
      "name": "Colour variations 1",
      "type": "Color",
      "capabilities": [
        {
          "min": "0",
          "max": "255",
          "name": "8 colour variations"
        }
      ]
    },
    {
      "name": "Colour variations 2",
      "type": "Color",
      "capabilities": [
        {
          "min": "0",
          "max": "255",
          "name": "8 colour variations"
        }
      ]
    },
    {
      "name": "No function 2",
      "type": "Unknown"
    },
    {
      "name": "No function 3",
      "type": "Unknown"
    },
    {
      "name": "No function 4",
      "type": "Unknown"
    }
  ],
  "modes": [
    {
      "name": "3-channel",
      "totalChannels": 3,
      "channels": [
        "Red",
        "Green",
        "Blue"
      ]
    },
    {
      "name": "4-channel",
      "totalChannels": 4,
      "channels": [
        "Colour Macro 1",
        "Colour Macro 2",
        "Colour Macro 3",
        "Colour Macro 4"
      ]
    },
    {
      "name": "5-channel",
      "totalChannels": 5,
      "channels": [
        "Red",
        "Green",
        "Blue",
        "Power Out 1",
        "Power Out 2"
      ]
    },
    {
      "name": "6-channel",
      "totalChannels": 6,
      "channels": [
        "Red 1 + 2",
        "Green 1 + 2",
        "Blue 1 + 2",
        "Red 3 + 4",
        "Green 3 + 4",
        "Blue 3 + 4"
      ]
    },
    {
      "name": "7-channel",
      "totalChannels": 7,
      "channels": [
        "Red",
        "Green",
        "Blue",
        "Master Dimmer",
        "Music Control / Strobe",
        "Power Out 1",
        "Power Out 2"
      ]
    },
    {
      "name": "8-channel",
      "totalChannels": 8,
      "channels": [
        "Programs",
        "Master Dimmer",
        "Strobe",
        "Red",
        "Green",
        "Blue",
        "Power Out 1",
        "Power Out 2"
      ]
    },
    {
      "name": "12-channel",
      "totalChannels": 12,
      "channels": [
        "Red",
        "Green",
        "Blue",
        "Red 2",
        "Green 2",
        "Blue 2",
        "Red 3",
        "Green 3",
        "Blue 3",
        "Red 4",
        "Green 4",
        "Blue 4"
      ]
    },
    {
      "name": "17-channel",
      "totalChannels": 17,
      "channels": [
        "Programs",
        "Master Dimmer",
        "Strobe",
        "Red 1",
        "Green 1",
        "Blue 1",
        "Red 2",
        "Green 2",
        "Blue 2",
        "Red 3",
        "Green 3",
        "Blue 3",
        "Red 4",
        "Green 4",
        "Blue 4",
        "Power Out 1",
        "Power Out 2"
      ]
    }
  ],
  "physical": {
    "bulb": {
      "type": "LED",
      "lumens": "0",
      "colourTemperature": "0"
    },
    "dimensions": {
      "weight": "8.8",
      "width": "1005",
      "height": "285",
      "depth": "80"
    },
    "lens": {
      "name": "Other",
      "degreesMin": "50",
      "degreesMax": "50"
    },
    "focus": {
      "type": "Fixed",
      "panMax": "0",
      "tiltMax": "0"
    },
    "technical": {
      "powerConsumption": "55",
      "dmxConnector": "3-pin"
    }
  }
}