{
  "version": "1.2",
  "manufacturer": "American DJ",
  "model": "Mega Bar RGBA",
  "type": "Par",
  "image": "",
  "productPage": "",
  "manual": "",
  "author": "Gary M",
  "channels": [
    {
      "name": "Red",
      "type": "Red"
    },
    {
      "name": "Green",
      "type": "Green"
    },
    {
      "name": "Blue",
      "type": "Blue"
    },
    {
      "name": "Amber",
      "type": "Amber"
    },
    {
      "name": "Color macro",
      "type": "Color"
    },
    {
      "name": "Strobe",
      "type": "Shutter"
    },
    {
      "name": "Master dimmer",
      "type": "Intensity"
    },
    {
      "name": "Red 1",
      "type": "Red"
    },
    {
      "name": "Green 1",
      "type": "Green"
    },
    {
      "name": "Blue 1",
      "type": "Blue"
    },
    {
      "name": "Amber 1",
      "type": "Amber"
    },
    {
      "name": "Red 2",
      "type": "Red"
    },
    {
      "name": "Red 3",
      "type": "Red"
    },
    {
      "name": "Red 4",
      "type": "Red"
    },
    {
      "name": "Red 5",
      "type": "Red"
    },
    {
      "name": "Red 6",
      "type": "Red"
    },
    {
      "name": "Red 7",
      "type": "Red"
    },
    {
      "name": "Red 8",
      "type": "Red"
    },
    {
      "name": "Green 2",
      "type": "Green"
    },
    {
      "name": "Green 3",
      "type": "Green"
    },
    {
      "name": "Green 4",
      "type": "Green"
    },
    {
      "name": "Green 5",
      "type": "Green"
    },
    {
      "name": "Green 6",
      "type": "Green"
    },
    {
      "name": "Green 7",
      "type": "Green"
    },
    {
      "name": "Green 8",
      "type": "Green"
    },
    {
      "name": "Blue 2",
      "type": "Blue"
    },
    {
      "name": "Blue 3",
      "type": "Blue"
    },
    {
      "name": "Blue 4",
      "type": "Blue"
    },
    {
      "name": "Blue 5",
      "type": "Blue"
    },
    {
      "name": "Blue 6",
      "type": "Blue"
    },
    {
      "name": "Blue 7",
      "type": "Blue"
    },
    {
      "name": "Blue 8",
      "type": "Blue"
    },
    {
      "name": "Amber 2",
      "type": "Amber"
    },
    {
      "name": "Amber 3",
      "type": "Amber"
    },
    {
      "name": "Amber 4",
      "type": "Amber"
    },
    {
      "name": "Amber 5",
      "type": "Amber"
    },
    {
      "name": "Amber 6",
      "type": "Amber"
    },
    {
      "name": "Amber 7",
      "type": "Amber"
    },
    {
      "name": "Amber 8",
      "type": "Amber"
    },
    {
      "name": "Programs",
      "type": "Maintenance",
      "capabilities": [
        {
          "min": "0",
          "max": "15",
          "name": "NO FUNCTION"
        },
        {
          "min": "16",
          "max": "25",
          "name": "PROGRAM 1"
        },
        {
          "min": "26",
          "max": "35",
          "name": "PROGRAM 2"
        },
        {
          "min": "36",
          "max": "45",
          "name": "PROGRAM 3"
        },
        {
          "min": "46",
          "max": "55",
          "name": "PROGRAM 4"
        },
        {
          "min": "56",
          "max": "65",
          "name": "PROGRAM 5"
        },
        {
          "min": "66",
          "max": "75",
          "name": "PROGRAM 6"
        },
        {
          "min": "76",
          "max": "85",
          "name": "PROGRAM 7"
        },
        {
          "min": "86",
          "max": "95",
          "name": "PROGRAM 8"
        },
        {
          "min": "96",
          "max": "105",
          "name": "PROGRAM 9"
        },
        {
          "min": "106",
          "max": "115",
          "name": "PROGRAM 10"
        },
        {
          "min": "116",
          "max": "125",
          "name": "PROGRAM 11"
        },
        {
          "min": "126",
          "max": "135",
          "name": "PROGRAM 12"
        },
        {
          "min": "136",
          "max": "145",
          "name": "PROGRAM 13"
        },
        {
          "min": "146",
          "max": "155",
          "name": "PROGRAM 14"
        },
        {
          "min": "156",
          "max": "165",
          "name": "PROGRAM 15"
        },
        {
          "min": "166",
          "max": "175",
          "name": "PROGRAM 16"
        },
        {
          "min": "176",
          "max": "185",
          "name": "PROGRAM 17"
        },
        {
          "min": "186",
          "max": "195",
          "name": "PROGRAM 18"
        },
        {
          "min": "196",
          "max": "205",
          "name": "PROGRAM 19"
        },
        {
          "min": "206",
          "max": "215",
          "name": "PROGRAM 20"
        },
        {
          "min": "216",
          "max": "225",
          "name": "PROGRAM 21"
        },
        {
          "min": "226",
          "max": "235",
          "name": "PROGRAM 22"
        },
        {
          "min": "236",
          "max": "245",
          "name": "AUTO RUN"
        },
        {
          "min": "246",
          "max": "255",
          "name": "SOUND ACTIVE"
        }
      ]
    },
    {
      "name": "Program Speed/Sound Sensitivity",
      "type": "Maintenance",
      "capabilities": [
        {
          "min": "0",
          "max": "255",
          "name": "SLOW - FAST/LEAST SENSITIVE - MOST SENSITIVE"
        }
      ]
    },
    {
      "name": "Red 1-4",
      "type": "Red"
    },
    {
      "name": "Green 1-4",
      "type": "Green"
    },
    {
      "name": "Blue 1-4",
      "type": "Blue"
    },
    {
      "name": "Amber 1-4",
      "type": "Amber"
    },
    {
      "name": "Red 5-8",
      "type": "Red"
    },
    {
      "name": "Green 5-8",
      "type": "Green"
    },
    {
      "name": "Blue 5-8",
      "type": "Blue"
    },
    {
      "name": "Amber 5-8",
      "type": "Amber"
    },
    {
      "name": "Red 1&2",
      "type": "Red"
    },
    {
      "name": "Green 1&2",
      "type": "Green"
    },
    {
      "name": "Blue 1&2",
      "type": "Blue"
    },
    {
      "name": "Amber 1&2",
      "type": "Amber"
    },
    {
      "name": "Red 3&4",
      "type": "Red"
    },
    {
      "name": "Green 3&4",
      "type": "Green"
    },
    {
      "name": "Blue 3&4",
      "type": "Blue"
    },
    {
      "name": "Amber 3&4",
      "type": "Amber"
    },
    {
      "name": "Red 5&6",
      "type": "Red"
    },
    {
      "name": "Green 5&6",
      "type": "Green"
    },
    {
      "name": "Blue 5&6",
      "type": "Blue"
    },
    {
      "name": "Amber 5&6",
      "type": "Amber"
    },
    {
      "name": "Red 7&8",
      "type": "Red"
    },
    {
      "name": "Green 7&8",
      "type": "Green"
    },
    {
      "name": "Blue 7&8",
      "type": "Blue"
    },
    {
      "name": "Amber 7&8",
      "type": "Amber"
    }
  ],
  "modes": [
    {
      "name": "Mode 1",
      "totalChannels": 7,
      "channels": [
        "Red",
        "Green",
        "Blue",
        "Amber",
        "Color macro",
        "Strobe",
        "Master dimmer"
      ]
    },
    {
      "name": "Mode 2",
      "totalChannels": 34,
      "channels": [
        "Red 1",
        "Green 1",
        "Blue 1",
        "Amber 1",
        "Red 2",
        "Green 2",
        "Blue 2",
        "Amber 2",
        "Red 3",
        "Green 3",
        "Blue 3",
        "Amber 3",
        "Red 4",
        "Green 4",
        "Blue 4",
        "Amber 4",
        "Red 5",
        "Green 5",
        "Blue 5",
        "Amber 5",
        "Red 6",
        "Green 6",
        "Blue 6",
        "Amber 6",
        "Red 7",
        "Green 7",
        "Blue 7",
        "Amber 7",
        "Red 8",
        "Green 8",
        "Blue 8",
        "Amber 8",
        "Strobe",
        "Master dimmer"
      ]
    },
    {
      "name": "Mode 3",
      "totalChannels": 4,
      "channels": [
        "Red",
        "Green",
        "Blue",
        "Amber"
      ]
    },
    {
      "name": "Mode 4",
      "totalChannels": 6,
      "channels": [
        "Red",
        "Green",
        "Blue",
        "Amber",
        "Strobe",
        "Master dimmer"
      ]
    },
    {
      "name": "Mode 5",
      "totalChannels": 9,
      "channels": [
        "Red",
        "Green",
        "Blue",
        "Amber",
        "Color macro",
        "Programs",
        "Program Speed/Sound Sensitivity",
        "Strobe",
        "Master dimmer"
      ]
    },
    {
      "name": "Mode 6",
      "totalChannels": 10,
      "channels": [
        "Red 1-4",
        "Green 1-4",
        "Blue 1-4",
        "Amber 1-4",
        "Red 5-8",
        "Green 5-8",
        "Blue 5-8",
        "Amber 5-8",
        "Strobe",
        "Master dimmer"
      ]
    },
    {
      "name": "Mode 7",
      "totalChannels": 18,
      "channels": [
        "Red 1&2",
        "Green 1&2",
        "Blue 1&2",
        "Amber 1&2",
        "Red 3&4",
        "Green 3&4",
        "Blue 3&4",
        "Amber 3&4",
        "Red 5&6",
        "Green 5&6",
        "Blue 5&6",
        "Amber 5&6",
        "Red 7&8",
        "Green 7&8",
        "Blue 7&8",
        "Amber 7&8",
        "Strobe",
        "Master dimmer"
      ]
    }
  ],
  "physical": {
    "bulb": {
      "type": "LED",
      "lumens": "0",
      "colourTemperature": "0"
    },
    "dimensions": {
      "weight": "2.7",
      "width": "1060",
      "height": "145",
      "depth": "73"
    },
    "lens": {
      "name": "Other",
      "degreesMin": "0",
      "degreesMax": "0"
    },
    "focus": {
      "type": "Head",
      "panMax": "0",
      "tiltMax": "0"
    },
    "technical": {
      "powerConsumption": "32",
      "dmxConnector": "3-pin"
    }
  }
}